mynblep-12.dist-info/entry_points.txt
mynblep-12.dist-info/METADATA
mynblep-12.dist-info/COPYING
mynblep-12.dist-info/WHEEL
mynblep-12.dist-info/top_level.txt
mynblep-12.dist-info/RECORD
mynblep/const.py
mynblep/__init__.py
mynblep/shapes.py
mynblep/warmup.py
mynblep/paste.py
mynblep/minblep.py
mynblep/paste_turbo/pasteminbleps.cpython-37m-x86_64-linux-gnu.so
mynblep/paste_turbo/pasteminbleps.pyx
mynblep/paste_turbo/__init__.py
mynblep/paste_turbo/pasteminbleps.pyxbld
