Metadata-Version: 2.1
Name: mynblep
Version: 12
Summary: MinBLEPs library including fast naive waveform conversion
Home-page: https://github.com/combatopera/mynblep
Author: Andrzej Cichocki and contributors
License: UNKNOWN
Platform: UNKNOWN
